[
  {
    "description": "Show Command Palette",
    "windows": "Ctrl+Shift+P, F1",
    "macos": "⇧⌘P, F1 ",
    "linux": "Ctrl+Shift+P, F1",
    "myshortcut": ""
  },
  {
    "description": "Quick Open, Go to File…",
    "windows": "Ctrl+P",
    "macos": "⌘P",
    "linux": "Ctrl+P",
    "myshortcut": ""
  },
  {
    "description": "New window/instance",
    "windows": "Ctrl+Shift+N",
    "macos": "⇧⌘N",
    "linux": "Ctrl+Shift+N ",
    "myshortcut": ""
  },
  {
    "description": "Close window/instance",
    "windows": "Ctrl+Shift+W",
    "macos": "⌘W ",
    "linux": "Ctrl+W",
    "myshortcut": ""
  },
  {
    "description": "User Settings",
    "windows": "Ctrl+,",
    "macos": "⌘,",
    "linux": "Ctrl+, ",
    "myshortcut": ""
  },
  {
    "description": "Keyboard Shortcuts",
    "windows": "Ctrl+K Ctrl+S",
    "macos": "⌘K ⌘S ",
    "linux": "Ctrl+K Ctrl+S",
    "myshortcut": ""
  }
]
